odoo/addons/account_sequence_option/README.rst
odoo/addons/account_sequence_option/__init__.py
odoo/addons/account_sequence_option/__manifest__.py
odoo/addons/account_sequence_option/data/account_sequence_option.xml
odoo/addons/account_sequence_option/demo/account_demo_options.xml
odoo/addons/account_sequence_option/i18n/account_sequence_option.pot
odoo/addons/account_sequence_option/models/__init__.py
odoo/addons/account_sequence_option/models/account_move.py
odoo/addons/account_sequence_option/models/sequence_option.py
odoo/addons/account_sequence_option/readme/CONTRIBUTORS.rst
odoo/addons/account_sequence_option/readme/DESCRIPTION.rst
odoo/addons/account_sequence_option/static/description/icon.png
odoo/addons/account_sequence_option/static/description/index.html
odoo/addons/account_sequence_option/tests/__init__.py
odoo/addons/account_sequence_option/tests/test_account_sequence_option.py
odoo/addons/account_sequence_option/views/account_move_views.xml
odoo14_addon_account_sequence_option-14.0.1.0.2.dist-info/METADATA
odoo14_addon_account_sequence_option-14.0.1.0.2.dist-info/WHEEL
odoo14_addon_account_sequence_option-14.0.1.0.2.dist-info/top_level.txt
odoo14_addon_account_sequence_option-14.0.1.0.2.dist-info/RECORD
