Metadata-Version: 2.1
Name: odoo14-addon-account-sequence-option
Version: 14.0.1.0.2
Summary: Manage sequence options for account.move, i.e., invoice, bill, entry
Home-page: https://github.com/OCA/account-financial-tools
Author: Ecosoft, Odoo Community Association (OCA)
Author-email: support@odoo-community.org
License: LGPL-3
Platform: UNKNOWN
Classifier: Programming Language :: Python
Classifier: Framework :: Odoo
Classifier: Framework :: Odoo :: 14.0
Classifier: License :: OSI Approved :: GNU Lesser General Public License v3 (LGPLv3)
Classifier: Development Status :: 3 - Alpha
Requires-Python: >=3.6
Requires-Dist: odoo14-addon-base-sequence-option
Requires-Dist: odoo (<14.1dev,>=14.0a)
